tree_sitter_rune-0.0.1.dist-info/RECORD
tree_sitter_rune-0.0.1.dist-info/WHEEL
tree_sitter_rune-0.0.1.dist-info/top_level.txt
tree_sitter_rune-0.0.1.dist-info/METADATA
tree_sitter_rune/__init__.pyi
tree_sitter_rune/binding.c
tree_sitter_rune/__init__.py
tree_sitter_rune/py.typed
tree_sitter_rune/_binding.abi3.so
