Metadata-Version: 2.4
Name: tree-sitter-rune
Version: 0.0.1
Summary: Rune grammar for tree-sitter
Author-email: Zhuhao Wang <zhuhaow@gmail.com>
License: MIT
Project-URL: Homepage, https://github.com/zhuhaow/tree-sitter-rune
Keywords: incremental,parsing,tree-sitter,rune
Classifier: Intended Audience :: Developers
Classifier: Topic :: Software Development :: Compilers
Classifier: Topic :: Text Processing :: Linguistic
Classifier: Typing :: Typed
Requires-Python: >=3.10
Provides-Extra: core
Requires-Dist: tree-sitter~=0.24; extra == "core"
